{
  "expected" : {
    "left" : {
      "avg" : {
        "ax" : "179",
        "cyl" : "-4.25",
        "sph" : "+1.00"
      },
      "r1" : {
        "ax" : "179",
        "cyl" : "-4.50",
        "sph" : "+1.25"
      },
      "r2" : {
        "ax" : "180",
        "cyl" : "-4.25",
        "sph" : "+0.75"
      },
      "r3" : {
        "ax" : "179",
        "cyl" : "-4.00",
        "sph" : "+1.00"
      }
    },
    "right" : {
      "avg" : {
        "ax" : "179",
        "cyl" : "-3.25",
        "sph" : "+0.75"
      },
      "r1" : {
        "ax" : "179",
        "cyl" : "-3.50",
        "sph" : "+0.75"
      },
      "r2" : {
        "ax" : "179",
        "cyl" : "-3.25",
        "sph" : "+1.00"
      },
      "r3" : {
        "ax" : "178",
        "cyl" : "-3.25",
        "sph" : "+0.50"
      }
    }
  },
  "shouldFail" : false
}